tlpytools/__init__.py
tlpytools/adls_server.py
tlpytools/azure_credential.py
tlpytools/config.py
tlpytools/data.py
tlpytools/data_store.py
tlpytools/env_config.py
tlpytools/log.py
tlpytools/sql_server.py
tlpytools/orca/README.md
tlpytools/orca/__init__.py
tlpytools/orca/__main__.py
tlpytools/orca/batch_task_runner.py
tlpytools/orca/cli.py
tlpytools/orca/orca_model_config_example.yaml
tlpytools/orca/orchestrator.py
tlpytools-0.1.14.dist-info/METADATA
tlpytools-0.1.14.dist-info/WHEEL
tlpytools-0.1.14.dist-info/entry_points.txt
tlpytools-0.1.14.dist-info/RECORD
