Metadata-Version: 2.4
Name: tlpytools
Version: 0.1.14
Summary: TransLink's Python Tools - A comprehensive toolkit for transportation modeling and forecasting
Project-URL: Homepage, https://github.com/TransLinkForecasting/tlpytools
Project-URL: Bug Tracker, https://github.com/TransLinkForecasting/tlpytools/issues
Author-email: Forecasting TransLink <forecasting@translink.ca>
Classifier: Development Status :: 4 - Beta
Classifier: Intended Audience :: Science/Research
Classifier: License :: Other/Proprietary License
Classifier: Operating System :: OS Independent
Classifier: Programming Language :: Python :: 3
Classifier: Programming Language :: Python :: 3.10
Classifier: Programming Language :: Python :: 3.11
Classifier: Topic :: Scientific/Engineering
Classifier: Topic :: Scientific/Engineering :: GIS
Requires-Python: <3.11,>=3.10.0
Requires-Dist: azure-core>=1.34
Requires-Dist: azure-identity-broker>=1.3.0
Requires-Dist: azure-identity>=1.23
Requires-Dist: azure-storage-blob>=12.24
Requires-Dist: azure-storage-file-datalake>=12.18
Requires-Dist: coverage>=7.10.6
Requires-Dist: cryptography>=3.4.7
Requires-Dist: cryptpandas>=0.1.1
Requires-Dist: numpy>=1.18
Requires-Dist: openmatrix>=0.3
Requires-Dist: pandas>=1.1
Requires-Dist: pyodbc>=4.0
Requires-Dist: python-dotenv>=1.0.0
Requires-Dist: pyyaml>=5.4
Requires-Dist: sqlalchemy>=1.4
Provides-Extra: dev
Requires-Dist: black>=23.0.0; extra == 'dev'
Requires-Dist: branca>=0.6.0; extra == 'dev'
Requires-Dist: cartopy>=0.21.0; extra == 'dev'
Requires-Dist: contextily>=1.5.0; extra == 'dev'
Requires-Dist: cycler>=0.11.0; extra == 'dev'
Requires-Dist: dash-bootstrap-components>=2.0.4; extra == 'dev'
Requires-Dist: dash-extensions>=1.0.0; extra == 'dev'
Requires-Dist: dash-leaflet>=0.1.0; extra == 'dev'
Requires-Dist: dash>=2.14.0; extra == 'dev'
Requires-Dist: fiona>=1.9.0; extra == 'dev'
Requires-Dist: folium>=0.14.0; extra == 'dev'
Requires-Dist: geopandas>=0.13.0; extra == 'dev'
Requires-Dist: ipykernel>=6.25.0; extra == 'dev'
Requires-Dist: jupyter>=1.0.0; extra == 'dev'
Requires-Dist: kiwisolver>=1.4.0; extra == 'dev'
Requires-Dist: mypy>=1.5.0; extra == 'dev'
Requires-Dist: notebook>=7.0.0; extra == 'dev'
Requires-Dist: openpyxl>=3.1.5; extra == 'dev'
Requires-Dist: panel>=1.3.0; extra == 'dev'
Requires-Dist: plotly>=5.17.0; extra == 'dev'
Requires-Dist: polars>=1.35.2; extra == 'dev'
Requires-Dist: polyline>=2.0.0; extra == 'dev'
Requires-Dist: pre-commit>=3.4.0; extra == 'dev'
Requires-Dist: pyproj>=3.4.0; extra == 'dev'
Requires-Dist: pytest-cov>=4.1.0; extra == 'dev'
Requires-Dist: pytest>=7.4.0; extra == 'dev'
Requires-Dist: rtree>=1.0.0; extra == 'dev'
Requires-Dist: ruff>=0.1.0; extra == 'dev'
Requires-Dist: seaborn>=0.13.2; extra == 'dev'
Requires-Dist: shapely>=2.0.0; extra == 'dev'
Provides-Extra: orca
Requires-Dist: psutil>=5.8.0; extra == 'orca'
Requires-Dist: unittest-xml-reporting>=3.2.0; extra == 'orca'
